[
  {
    "구분": "교양필수",
    "학수번호": "GELI005",
    "교과목명": "학문세계의탐구 I",
    "학년": 1,
    "학기": null,
    "필수선수": null,
    "권장선수": null,
    "실험실습": null,
    "세부전공": null,
    "학점": 3.0,
    "시간": 3.0,
    "전공역량": null,
    "대학": "디자인조형학부",
    "학과": "디자인조형학부",
    "개설학과": "디자인조형학부",
    "내용": null,
    "메모": null,
    "개설횟수": 0,
    "syllabus_kr": "본 교과목은 학습자 주도형 토론 중심 수업으로 다양한 학문 세계를 탐구하며 비판적·창의적·융합적 사고 능력을 배양하는 것을 목적으로 한다. 학문세계의탐구Ⅰ은 토론과 협업을 통해 인간을 이해하고 가치를 탐구하는 교양필수 과목이다.",
    "syllabus_en": "The course explores the academic world across various disciplines and aims to cultivate critical, creative, and convergent thinking competencies with learner-driven, discussion-based instruction._x000D_\nExploration of the Academic World I is a General Education"
  },
  {
    "구분": "교양필수",
    "학수번호": "GEWR002",
    "교과목명": "글쓰기",
    "학년": 1,
    "학기": 1.0,
    "필수선수": null,
    "권장선수": null,
    "실험실습": null,
    "세부전공": null,
    "학점": 3.0,
    "시간": 3.0,
    "전공역량": null,
    "대학": "디자인조형학부",
    "학과": "디자인조형학부",
    "개설학과": "디자인조형학부",
    "내용": null,
    "메모": null,
    "개설횟수": 0,
    "syllabus_kr": "<글쓰기>는 ‘글쓰기의 기초’를 훈련하는 과목으로, 대학 수학 능력의 기본이 되는 사고력과 자기 표현력을 기르는 것을 목표로 한다. 학업 과정에서?요구되는 글쓰기의 특성을 이해하고, 이를 바탕으로 글쓰기를 체계적으로 훈련한다. <글쓰기>는 전교 공통의 과정으로 1학",
    "syllabus_en": "College Writing is an introductory writing course intended to advance students’ critical thinking skills and self-expression?basic skills required for college studies. In this course, students will gain a better understanding of the specific techniques n"
  },
  {
    "구분": "교양필수",
    "학수번호": "IFLS800",
    "교과목명": "Academic English I",
    "학년": 1,
    "학기": null,
    "필수선수": null,
    "권장선수": null,
    "실험실습": null,
    "세부전공": null,
    "학점": 2.0,
    "시간": 2.0,
    "전공역량": null,
    "대학": "디자인조형학부",
    "학과": "디자인조형학부",
    "개설학과": "디자인조형학부",
    "내용": null,
    "메모": null,
    "개설횟수": 0,
    "syllabus_kr": "이 수업은 학생들의 학술관련 영어능력 및 의사소통능력을 향상시키는 데 목적이 있다. 학업 관련 모든 영역에서 활용 가능한 전반적인 영어능력 향상을 위해 학술 내용을 바탕으로 수업을 진행하며, 학생들이 실제 상황에서 구사할 수 있는 영어능력 향상에 초점을 맞춘 다 ",
    "syllabus_en": "The objective of this course is to enhance students’ communicative competence in English. Academic content is covered to improve overall proficiency in all areas of English communication as it relates to academic studies. Basic language skills are develo"
  },
  {
    "구분": "교양필수",
    "학수번호": "GEKS007",
    "교과목명": "[진로창업]1학년세미나 I",
    "학년": 1,
    "학기": 1.0,
    "필수선수": null,
    "권장선수": null,
    "실험실습": null,
    "세부전공": null,
    "학점": 1.0,
    "시간": 1.0,
    "전공역량": null,
    "대학": "디자인조형학부",
    "학과": "디자인조형학부",
    "개설학과": "디자인조형학부",
    "내용": null,
    "메모": null,
    "개설횟수": 0,
    "syllabus_kr": "[진로·창업] 1학년세미나Ⅰ은 멘토 특성을 지닌 교양필수 교과목으로서, 1학년 세미나 지도교수의 통솔 하에 대학생활에 적응하고 대학생으로서 진로(연구, 취업, 창업)를 설계할 수 있도록, 온라인 합동강좌 수강, 개별 지도 및 면담, 교내외 다양한 프로그램 참여 등으로 ",
    "syllabus_en": "[Career·Entrepreneurship] Freshmen Seminar is a required course for first-year students, which provides fitting in university and career explorations. It includes academic advising, counseling with professors, seminars or special online lectures by KU fa"
  },
  {
    "구분": "교양필수",
    "학수번호": "GEKS008",
    "교과목명": "[진로창업]1학년세미나 I",
    "학년": 1,
    "학기": 2.0,
    "필수선수": null,
    "권장선수": null,
    "실험실습": null,
    "세부전공": null,
    "학점": 1.0,
    "시간": 1.0,
    "전공역량": null,
    "대학": "디자인조형학부",
    "학과": "디자인조형학부",
    "개설학과": "디자인조형학부",
    "내용": null,
    "메모": null,
    "개설횟수": 0,
    "syllabus_kr": "[진로·창업] 1학년세미나Ⅱ는 멘토 특성을 지닌 교양필수 교과목으로서, 1학년 세미나 지도교수의 통솔 하에 학교에 대한 소속감을 강화하고 창직 및 창업 등의 진로 방향성을 고민해볼 수 있도록, 온라인 합동강좌 수강, 개별 지도 및 면담, 교내외 다양한 프로그램 참여  ",
    "syllabus_en": "[Career·Entrepreneurship] Freshmen Seminar is a required course for first-year students, offering mentorship and guidance in career directions such as entrepreneurship. It includes academic advising, counseling with professors, seminars, and special onli"
  },
  {
    "구분": "교양필수",
    "학수번호": "GECT002",
    "교과목명": "[진로창업]SW프로그래밍의기초",
    "학년": 1,
    "학기": 1.0,
    "필수선수": null,
    "권장선수": null,
    "실험실습": null,
    "세부전공": null,
    "학점": 3.0,
    "시간": 3.0,
    "전공역량": null,
    "대학": "디자인조형학부",
    "학과": "디자인조형학부",
    "개설학과": "디자인조형학부",
    "내용": null,
    "메모": null,
    "개설횟수": 0,
    "syllabus_kr": "이 과목은 컴퓨팅 사고와 프로그래밍의 기본 원리를 소개하는 과정이다. 소프트웨어의 근간이 되는 프로그래밍 언어에 대한 체계적인 이해를 바탕으로, Python 언어를 통해 기본 문법, 데이터 구조 및 제어 구조의 핵심 개념을 학습한다. 학생들은 이 과목을 통해 프로그래밍",
    "syllabus_en": "This course introduces the fundamental principles of computing thinking and programming. Building on a systematic understanding of the programming languages that form the foundation of software, students will learn essential concepts of syntax, data struc"
  },
  {
    "구분": "교양필수",
    "학수번호": "GECT003",
    "교과목명": "[진로창업]데이터과학과인공지능",
    "학년": 1,
    "학기": 2.0,
    "필수선수": null,
    "권장선수": null,
    "실험실습": null,
    "세부전공": null,
    "학점": 3.0,
    "시간": 3.0,
    "전공역량": null,
    "대학": "디자인조형학부",
    "학과": "디자인조형학부",
    "개설학과": "디자인조형학부",
    "내용": null,
    "메모": null,
    "개설횟수": 0,
    "syllabus_kr": "이 과목은 데이터를 다루고 분석할 수 있는 역량과 인공지능 기술을 이해하고 자기의 일에 활용할 수 있는 방법을 학습하는 과정이다. 기초적인 데이터과학 및 인공지능 핵심 개념을 학습하고, 각 계열별 특성에 맞는 데이터를 활용한 실습을 통해 실제 데이터를 다루고 인",
    "syllabus_en": "This course aims to develop the ability to handle and analyze data, understand artificial intelligence technologies, and learn how to apply them in one's field of work. It covers fundamental concepts of data science and artificial intelligence, and throug"
  },
  {
    "구분": "교양필수",
    "학수번호": "GEBT001",
    "교과목명": "[진로창업]생명과학의세계",
    "학년": 1,
    "학기": null,
    "필수선수": null,
    "권장선수": null,
    "실험실습": null,
    "세부전공": null,
    "학점": 3.0,
    "시간": 3.0,
    "전공역량": null,
    "대학": "디자인조형학부",
    "학과": "디자인조형학부",
    "개설학과": "디자인조형학부",
    "내용": null,
    "메모": null,
    "개설횟수": 0,
    "syllabus_kr": "생명과학의 세계는 생명공학의 기초 지식과 생명현상을 이용한 융복합 기술의 다양한 사례를 살펴봄으로써 변화하는 미래 환경을 대비하고 선도할 수 있는 융합적 사고를 함양하는 강좌이다.",
    "syllabus_en": "This is a course that fosters convergent thinking to prepare for and lead the changing future environment by examining basic knowledge of biotechnology and various examples of convergence technologies using life phenomena."
  },
  {
    "구분": "교양필수",
    "학수번호": "ARDE200",
    "교과목명": "2D기초조형",
    "학년": 1,
    "학기": 1.0,
    "필수선수": null,
    "권장선수": null,
    "실험실습": null,
    "세부전공": null,
    "학점": 2.0,
    "시간": 2.0,
    "전공역량": null,
    "대학": "디자인조형학부",
    "학과": "디자인조형학부",
    "개설학과": "디자인조형학부",
    "내용": null,
    "메모": null,
    "개설횟수": 0,
    "syllabus_kr": "",
    "syllabus_en": ""
  },
  {
    "구분": "교양필수",
    "학수번호": "ARDE270",
    "교과목명": "기초디자인-2D",
    "학년": 1,
    "학기": 1.0,
    "필수선수": null,
    "권장선수": null,
    "실험실습": null,
    "세부전공": "산업정보디자인",
    "학점": 2.0,
    "시간": 2.0,
    "전공역량": null,
    "대학": "디자인조형학부",
    "학과": "디자인조형학부",
    "개설학과": "디자인조형학부",
    "내용": null,
    "메모": null,
    "개설횟수": 0,
    "syllabus_kr": "",
    "syllabus_en": ""
  },
  {
    "구분": "전공필수",
    "학수번호": "ARDE223",
    "교과목명": "제품디자인스튜디오I",
    "학년": 2,
    "학기": 1.0,
    "필수선수": null,
    "권장선수": null,
    "실험실습": null,
    "세부전공": "산업정보디자인",
    "학점": 2.0,
    "시간": 4.0,
    "전공역량": null,
    "대학": "디자인조형학부",
    "학과": "디자인조형학부",
    "개설학과": "디자인조형학부",
    "내용": null,
    "메모": null,
    "개설횟수": 0,
    "syllabus_kr": "",
    "syllabus_en": ""
  },
  {
    "구분": "전공필수",
    "학수번호": "ARDE224",
    "교과목명": "제품디자인스튜디오II",
    "학년": 2,
    "학기": 2.0,
    "필수선수": null,
    "권장선수": null,
    "실험실습": null,
    "세부전공": "산업정보디자인",
    "학점": 2.0,
    "시간": 4.0,
    "전공역량": null,
    "대학": "디자인조형학부",
    "학과": "디자인조형학부",
    "개설학과": "디자인조형학부",
    "내용": null,
    "메모": null,
    "개설횟수": 0,
    "syllabus_kr": "",
    "syllabus_en": ""
  },
  {
    "구분": "전공필수",
    "학수번호": "ARDE311",
    "교과목명": "제품디자인스튜디오III",
    "학년": 3,
    "학기": 1.0,
    "필수선수": null,
    "권장선수": null,
    "실험실습": null,
    "세부전공": "산업정보디자인",
    "학점": 2.0,
    "시간": 4.0,
    "전공역량": null,
    "대학": "디자인조형학부",
    "학과": "디자인조형학부",
    "개설학과": "디자인조형학부",
    "내용": null,
    "메모": null,
    "개설횟수": 0,
    "syllabus_kr": "",
    "syllabus_en": ""
  },
  {
    "구분": "전공필수",
    "학수번호": "ARDE312",
    "교과목명": "제품디자인스튜디오IV",
    "학년": 3,
    "학기": 2.0,
    "필수선수": null,
    "권장선수": null,
    "실험실습": null,
    "세부전공": "산업정보디자인",
    "학점": 2.0,
    "시간": 4.0,
    "전공역량": null,
    "대학": "디자인조형학부",
    "학과": "디자인조형학부",
    "개설학과": "디자인조형학부",
    "내용": null,
    "메모": null,
    "개설횟수": 0,
    "syllabus_kr": "",
    "syllabus_en": ""
  },
  {
    "구분": "전공필수",
    "학수번호": "ARDE416",
    "교과목명": "졸업작품(우수ARDE411 졸업연구)",
    "학년": 4,
    "학기": 2.0,
    "필수선수": null,
    "권장선수": null,
    "실험실습": null,
    "세부전공": "산업정보디자인",
    "학점": 2.0,
    "시간": 4.0,
    "전공역량": null,
    "대학": "디자인조형학부",
    "학과": "디자인조형학부",
    "개설학과": "디자인조형학부",
    "내용": null,
    "메모": "★졸업전필수",
    "개설횟수": 0,
    "syllabus_kr": "",
    "syllabus_en": ""
  },
  {
    "구분": "전공선택",
    "학수번호": "ARDE212",
    "교과목명": "디자인표현기법",
    "학년": 1,
    "학기": 2.0,
    "필수선수": null,
    "권장선수": null,
    "실험실습": null,
    "세부전공": "산업정보디자인",
    "학점": 2.0,
    "시간": 2.0,
    "전공역량": null,
    "대학": "디자인조형학부",
    "학과": "디자인조형학부",
    "개설학과": "디자인조형학부",
    "내용": null,
    "메모": null,
    "개설횟수": 0,
    "syllabus_kr": "",
    "syllabus_en": ""
  },
  {
    "구분": "전공선택",
    "학수번호": "ARDE285",
    "교과목명": "3D그래픽스",
    "학년": 1,
    "학기": 2.0,
    "필수선수": null,
    "권장선수": null,
    "실험실습": null,
    "세부전공": "산업정보디자인",
    "학점": 2.0,
    "시간": 2.0,
    "전공역량": null,
    "대학": "디자인조형학부",
    "학과": "디자인조형학부",
    "개설학과": "디자인조형학부",
    "내용": null,
    "메모": "우수:ARDE217 3D컴퓨터그래픽",
    "개설횟수": 0,
    "syllabus_kr": "",
    "syllabus_en": ""
  },
  {
    "구분": "전공선택",
    "학수번호": "ARDE275",
    "교과목명": "기초디자인-3D",
    "학년": 2,
    "학기": 1.0,
    "필수선수": null,
    "권장선수": null,
    "실험실습": null,
    "세부전공": "산업정보디자인",
    "학점": 2.0,
    "시간": 2.0,
    "전공역량": null,
    "대학": "디자인조형학부",
    "학과": "디자인조형학부",
    "개설학과": "디자인조형학부",
    "내용": null,
    "메모": null,
    "개설횟수": 0,
    "syllabus_kr": "",
    "syllabus_en": ""
  },
  {
    "구분": "전공선택",
    "학수번호": "ARDE218",
    "교과목명": "4D컴퓨터그래픽",
    "학년": 2,
    "학기": 2.0,
    "필수선수": null,
    "권장선수": null,
    "실험실습": null,
    "세부전공": "산업정보디자인",
    "학점": 2.0,
    "시간": 2.0,
    "전공역량": null,
    "대학": "디자인조형학부",
    "학과": "디자인조형학부",
    "개설학과": "디자인조형학부",
    "내용": null,
    "메모": null,
    "개설횟수": 0,
    "syllabus_kr": "",
    "syllabus_en": ""
  },
  {
    "구분": "전공선택",
    "학수번호": "ARDE225",
    "교과목명": "디자인관찰상",
    "학년": 2,
    "학기": 2.0,
    "필수선수": null,
    "권장선수": null,
    "실험실습": null,
    "세부전공": "산업정보디자인",
    "학점": 2.0,
    "시간": 2.0,
    "전공역량": null,
    "대학": "디자인조형학부",
    "학과": "디자인조형학부",
    "개설학과": "디자인조형학부",
    "내용": null,
    "메모": null,
    "개설횟수": 0,
    "syllabus_kr": "",
    "syllabus_en": ""
  },
  {
    "구분": "전공선택",
    "학수번호": "ARDE228",
    "교과목명": "재료와프로세스",
    "학년": 2,
    "학기": 2.0,
    "필수선수": null,
    "권장선수": null,
    "실험실습": null,
    "세부전공": "산업정보디자인",
    "학점": 2.0,
    "시간": 2.0,
    "전공역량": null,
    "대학": "디자인조형학부",
    "학과": "디자인조형학부",
    "개설학과": "디자인조형학부",
    "내용": null,
    "메모": null,
    "개설횟수": 0,
    "syllabus_kr": "",
    "syllabus_en": ""
  },
  {
    "구분": "전공선택",
    "학수번호": "ARDE229",
    "교과목명": "기초정보디자인",
    "학년": 2,
    "학기": 2.0,
    "필수선수": null,
    "권장선수": null,
    "실험실습": null,
    "세부전공": "산업정보디자인",
    "학점": 2.0,
    "시간": 2.0,
    "전공역량": null,
    "대학": "디자인조형학부",
    "학과": "디자인조형학부",
    "개설학과": "디자인조형학부",
    "내용": null,
    "메모": null,
    "개설횟수": 0,
    "syllabus_kr": "",
    "syllabus_en": ""
  },
  {
    "구분": "전공선택",
    "학수번호": "ARDE220",
    "교과목명": "디자인프로토타이핑",
    "학년": 2,
    "학기": 2.0,
    "필수선수": null,
    "권장선수": null,
    "실험실습": null,
    "세부전공": "산업정보디자인",
    "학점": 2.0,
    "시간": 2.0,
    "전공역량": null,
    "대학": "디자인조형학부",
    "학과": "디자인조형학부",
    "개설학과": "디자인조형학부",
    "내용": null,
    "메모": null,
    "개설횟수": 0,
    "syllabus_kr": "",
    "syllabus_en": ""
  },
  {
    "구분": "전공선택",
    "학수번호": "ARDE284",
    "교과목명": "디자인워크샵",
    "학년": 2,
    "학기": 2.0,
    "필수선수": null,
    "권장선수": null,
    "실험실습": null,
    "세부전공": "산업정보디자인",
    "학점": 2.0,
    "시간": 2.0,
    "전공역량": null,
    "대학": "디자인조형학부",
    "학과": "디자인조형학부",
    "개설학과": "디자인조형학부",
    "내용": null,
    "메모": null,
    "개설횟수": 0,
    "syllabus_kr": "",
    "syllabus_en": ""
  },
  {
    "구분": "전공선택",
    "학수번호": "ARDE230",
    "교과목명": "인터랙티브컴퓨팅",
    "학년": 2,
    "학기": 2.0,
    "필수선수": null,
    "권장선수": null,
    "실험실습": null,
    "세부전공": "산업정보디자인",
    "학점": 2.0,
    "시간": 2.0,
    "전공역량": null,
    "대학": "디자인조형학부",
    "학과": "디자인조형학부",
    "개설학과": "디자인조형학부",
    "내용": null,
    "메모": null,
    "개설횟수": 0,
    "syllabus_kr": "",
    "syllabus_en": ""
  },
  {
    "구분": "전공선택",
    "학수번호": "ARDE278",
    "교과목명": "기초정보조형",
    "학년": 2,
    "학기": 2.0,
    "필수선수": null,
    "권장선수": null,
    "실험실습": null,
    "세부전공": "산업정보디자인",
    "학점": 2.0,
    "시간": 2.0,
    "전공역량": null,
    "대학": "디자인조형학부",
    "학과": "디자인조형학부",
    "개설학과": "디자인조형학부",
    "내용": null,
    "메모": null,
    "개설횟수": 0,
    "syllabus_kr": "",
    "syllabus_en": ""
  },
  {
    "구분": "전공선택",
    "학수번호": "ARDE313",
    "교과목명": "디자인 인간요소",
    "학년": 3,
    "학기": 1.0,
    "필수선수": null,
    "권장선수": null,
    "실험실습": null,
    "세부전공": "산업정보디자인",
    "학점": 2.0,
    "시간": 2.0,
    "전공역량": null,
    "대학": "디자인조형학부",
    "학과": "디자인조형학부",
    "개설학과": "디자인조형학부",
    "내용": null,
    "메모": null,
    "개설횟수": 0,
    "syllabus_kr": "",
    "syllabus_en": ""
  },
  {
    "구분": "전공선택",
    "학수번호": "ARDE322",
    "교과목명": "디자인방법론",
    "학년": 3,
    "학기": 1.0,
    "필수선수": null,
    "권장선수": null,
    "실험실습": null,
    "세부전공": "산업정보디자인",
    "학점": 2.0,
    "시간": 2.0,
    "전공역량": null,
    "대학": "디자인조형학부",
    "학과": "디자인조형학부",
    "개설학과": "디자인조형학부",
    "내용": null,
    "메모": null,
    "개설횟수": 0,
    "syllabus_kr": "",
    "syllabus_en": ""
  },
  {
    "구분": "전공선택",
    "학수번호": "ARDE324",
    "교과목명": "인터랙션디자인",
    "학년": 3,
    "학기": 2.0,
    "필수선수": null,
    "권장선수": null,
    "실험실습": null,
    "세부전공": "산업정보디자인",
    "학점": 2.0,
    "시간": 2.0,
    "전공역량": null,
    "대학": "디자인조형학부",
    "학과": "디자인조형학부",
    "개설학과": "디자인조형학부",
    "내용": null,
    "메모": null,
    "개설횟수": 0,
    "syllabus_kr": "",
    "syllabus_en": ""
  },
  {
    "구분": "전공선택",
    "학수번호": "ARDE327",
    "교과목명": "공공디자인",
    "학년": 3,
    "학기": 2.0,
    "필수선수": null,
    "권장선수": null,
    "실험실습": null,
    "세부전공": "산업정보디자인",
    "학점": 2.0,
    "시간": 2.0,
    "전공역량": null,
    "대학": "디자인조형학부",
    "학과": "디자인조형학부",
    "개설학과": "디자인조형학부",
    "내용": null,
    "메모": null,
    "개설횟수": 0,
    "syllabus_kr": "",
    "syllabus_en": ""
  },
  {
    "구분": "전공선택",
    "학수번호": "ARDE314",
    "교과목명": "디자인마케팅",
    "학년": 3,
    "학기": 2.0,
    "필수선수": null,
    "권장선수": null,
    "실험실습": null,
    "세부전공": "산업정보디자인",
    "학점": 2.0,
    "시간": 2.0,
    "전공역량": null,
    "대학": "디자인조형학부",
    "학과": "디자인조형학부",
    "개설학과": "디자인조형학부",
    "내용": null,
    "메모": null,
    "개설횟수": 0,
    "syllabus_kr": "",
    "syllabus_en": ""
  },
  {
    "구분": "전공선택",
    "학수번호": "ARDE320",
    "교과목명": "디자인사고",
    "학년": 3,
    "학기": 2.0,
    "필수선수": null,
    "권장선수": null,
    "실험실습": null,
    "세부전공": "산업정보디자인",
    "학점": 2.0,
    "시간": 2.0,
    "전공역량": null,
    "대학": "디자인조형학부",
    "학과": "디자인조형학부",
    "개설학과": "디자인조형학부",
    "내용": null,
    "메모": null,
    "개설횟수": 0,
    "syllabus_kr": "",
    "syllabus_en": ""
  },
  {
    "구분": "전공선택",
    "학수번호": "ARDE323",
    "교과목명": "인터페이스디자인",
    "학년": 3,
    "학기": 2.0,
    "필수선수": null,
    "권장선수": null,
    "실험실습": null,
    "세부전공": "산업정보디자인",
    "학점": 2.0,
    "시간": 2.0,
    "전공역량": null,
    "대학": "디자인조형학부",
    "학과": "디자인조형학부",
    "개설학과": "디자인조형학부",
    "내용": null,
    "메모": null,
    "개설횟수": 0,
    "syllabus_kr": "",
    "syllabus_en": ""
  },
  {
    "구분": "전공선택",
    "학수번호": "ARDE330",
    "교과목명": "신개념가구디자인",
    "학년": 3,
    "학기": 2.0,
    "필수선수": null,
    "권장선수": null,
    "실험실습": null,
    "세부전공": "산업정보디자인",
    "학점": 2.0,
    "시간": 2.0,
    "전공역량": null,
    "대학": "디자인조형학부",
    "학과": "디자인조형학부",
    "개설학과": "디자인조형학부",
    "내용": null,
    "메모": null,
    "개설횟수": 0,
    "syllabus_kr": "",
    "syllabus_en": ""
  },
  {
    "구분": "전공선택",
    "학수번호": "ARDE415",
    "교과목명": "제품시스템디자인(통합설계)",
    "학년": 4,
    "학기": 1.0,
    "필수선수": null,
    "권장선수": null,
    "실험실습": null,
    "세부전공": "산업정보디자인",
    "학점": 2.0,
    "시간": 4.0,
    "전공역량": null,
    "대학": "디자인조형학부",
    "학과": "디자인조형학부",
    "개설학과": "디자인조형학부",
    "내용": null,
    "메모": "★졸업전필수",
    "개설횟수": 0,
    "syllabus_kr": "",
    "syllabus_en": ""
  },
  {
    "구분": "전공선택",
    "학수번호": "ARDE417",
    "교과목명": "제품개발(통합설계)",
    "학년": 4,
    "학기": 1.0,
    "필수선수": null,
    "권장선수": null,
    "실험실습": null,
    "세부전공": "산업정보디자인",
    "학점": 2.0,
    "시간": 4.0,
    "전공역량": null,
    "대학": "디자인조형학부",
    "학과": "디자인조형학부",
    "개설학과": "디자인조형학부",
    "내용": null,
    "메모": "★졸업전필수",
    "개설횟수": 0,
    "syllabus_kr": "",
    "syllabus_en": ""
  },
  {
    "구분": "전공선택",
    "학수번호": "ARDE414",
    "교과목명": "디지털디자인프로젝트",
    "학년": 4,
    "학기": 1.0,
    "필수선수": null,
    "권장선수": null,
    "실험실습": null,
    "세부전공": "산업정보디자인",
    "학점": 2.0,
    "시간": 2.0,
    "전공역량": null,
    "대학": "디자인조형학부",
    "학과": "디자인조형학부",
    "개설학과": "디자인조형학부",
    "내용": null,
    "메모": null,
    "개설횟수": 0,
    "syllabus_kr": "",
    "syllabus_en": ""
  },
  {
    "구분": "전공선택",
    "학수번호": "ARDE425",
    "교과목명": "디자인브랜딩",
    "학년": 4,
    "학기": 2.0,
    "필수선수": null,
    "권장선수": null,
    "실험실습": null,
    "세부전공": "산업정보디자인",
    "학점": 2.0,
    "시간": 2.0,
    "전공역량": null,
    "대학": "디자인조형학부",
    "학과": "디자인조형학부",
    "개설학과": "디자인조형학부",
    "내용": null,
    "메모": null,
    "개설횟수": 0,
    "syllabus_kr": "",
    "syllabus_en": ""
  },
  {
    "구분": "전공선택",
    "학수번호": "ARDE422",
    "교과목명": "포트폴리오",
    "학년": 4,
    "학기": 2.0,
    "필수선수": null,
    "권장선수": null,
    "실험실습": null,
    "세부전공": "산업정보디자인",
    "학점": 2.0,
    "시간": 2.0,
    "전공역량": null,
    "대학": "디자인조형학부",
    "학과": "디자인조형학부",
    "개설학과": "디자인조형학부",
    "내용": null,
    "메모": null,
    "개설횟수": 0,
    "syllabus_kr": "",
    "syllabus_en": ""
  },
  {
    "구분": "전공선택",
    "학수번호": "ARDE423",
    "교과목명": "디자인세미나",
    "학년": 4,
    "학기": 2.0,
    "필수선수": null,
    "권장선수": null,
    "실험실습": null,
    "세부전공": "산업정보디자인",
    "학점": 2.0,
    "시간": 2.0,
    "전공역량": null,
    "대학": "디자인조형학부",
    "학과": "디자인조형학부",
    "개설학과": "디자인조형학부",
    "내용": null,
    "메모": null,
    "개설횟수": 0,
    "syllabus_kr": "",
    "syllabus_en": ""
  },
  {
    "구분": "전공선택",
    "학수번호": "ARDE424",
    "교과목명": "디자인리서치연구",
    "학년": 4,
    "학기": 2.0,
    "필수선수": null,
    "권장선수": null,
    "실험실습": null,
    "세부전공": "산업정보디자인",
    "학점": 2.0,
    "시간": 2.0,
    "전공역량": null,
    "대학": "디자인조형학부",
    "학과": "디자인조형학부",
    "개설학과": "디자인조형학부",
    "내용": null,
    "메모": null,
    "개설횟수": 0,
    "syllabus_kr": "",
    "syllabus_en": ""
  },
  {
    "구분": "전공필수",
    "학수번호": "ARDE286",
    "교과목명": "선묘와드로잉",
    "학년": 1,
    "학기": 2.0,
    "필수선수": null,
    "권장선수": null,
    "실험실습": null,
    "세부전공": "조형미술",
    "학점": 2.0,
    "시간": 2.0,
    "전공역량": null,
    "대학": "디자인조형학부",
    "학과": "디자인조형학부",
    "개설학과": "디자인조형학부",
    "내용": null,
    "메모": "우수:ARDE257 드로잉실기",
    "개설횟수": 0,
    "syllabus_kr": "",
    "syllabus_en": ""
  },
  {
    "구분": "전공필수",
    "학수번호": "ARDE343",
    "교과목명": "현대회화기법",
    "학년": 2,
    "학기": 1.0,
    "필수선수": null,
    "권장선수": null,
    "실험실습": null,
    "세부전공": "조형미술",
    "학점": 2.0,
    "시간": 2.0,
    "전공역량": null,
    "대학": "디자인조형학부",
    "학과": "디자인조형학부",
    "개설학과": "디자인조형학부",
    "내용": null,
    "메모": null,
    "개설횟수": 0,
    "syllabus_kr": "",
    "syllabus_en": ""
  },
  {
    "구분": "전공필수",
    "학수번호": "ARDE293",
    "교과목명": "전통회화연구II",
    "학년": 2,
    "학기": 2.0,
    "필수선수": null,
    "권장선수": null,
    "실험실습": null,
    "세부전공": "조형미술",
    "학점": 2.0,
    "시간": 2.0,
    "전공역량": null,
    "대학": "디자인조형학부",
    "학과": "디자인조형학부",
    "개설학과": "디자인조형학부",
    "내용": null,
    "메모": "우수:ARDE369한국화0채색I",
    "개설횟수": 0,
    "syllabus_kr": "",
    "syllabus_en": ""
  },
  {
    "구분": "전공필수",
    "학수번호": "ARDE338",
    "교과목명": "한국화II-색채기법",
    "학년": 3,
    "학기": 1.0,
    "필수선수": null,
    "권장선수": null,
    "실험실습": null,
    "세부전공": "조형미술",
    "학점": 2.0,
    "시간": 2.0,
    "전공역량": null,
    "대학": "디자인조형학부",
    "학과": "디자인조형학부",
    "개설학과": "디자인조형학부",
    "내용": null,
    "메모": null,
    "개설횟수": 0,
    "syllabus_kr": "",
    "syllabus_en": ""
  },
  {
    "구분": "전공필수",
    "학수번호": "ARDE374",
    "교과목명": "미술사I",
    "학년": 3,
    "학기": 1.0,
    "필수선수": null,
    "권장선수": null,
    "실험실습": null,
    "세부전공": "조형미술",
    "학점": 2.0,
    "시간": 2.0,
    "전공역량": null,
    "대학": "디자인조형학부",
    "학과": "디자인조형학부",
    "개설학과": "디자인조형학부",
    "내용": null,
    "메모": "우수:ARDE244 개성계획디자인",
    "개설횟수": 0,
    "syllabus_kr": "",
    "syllabus_en": ""
  },
  {
    "구분": "전공필수",
    "학수번호": "ARDE435",
    "교과목명": "한국문화STUDIOI",
    "학년": 4,
    "학기": 1.0,
    "필수선수": null,
    "권장선수": null,
    "실험실습": null,
    "세부전공": "조형미술",
    "학점": 2.0,
    "시간": 4.0,
    "전공역량": null,
    "대학": "디자인조형학부",
    "학과": "디자인조형학부",
    "개설학과": "디자인조형학부",
    "내용": null,
    "메모": "★졸업전필수",
    "개설횟수": 0,
    "syllabus_kr": "",
    "syllabus_en": ""
  },
  {
    "구분": "전공선택",
    "학수번호": "ARDE289",
    "교과목명": "현대미술워크샵",
    "학년": 1,
    "학기": 2.0,
    "필수선수": null,
    "권장선수": null,
    "실험실습": null,
    "세부전공": "조형미술",
    "학점": 2.0,
    "시간": 2.0,
    "전공역량": null,
    "대학": "디자인조형학부",
    "학과": "디자인조형학부",
    "개설학과": "디자인조형학부",
    "내용": null,
    "메모": "우수:ARDE264 문화연구",
    "개설횟수": 0,
    "syllabus_kr": "",
    "syllabus_en": ""
  },
  {
    "구분": "전공선택",
    "학수번호": "ARDE288",
    "교과목명": "기초매체연구",
    "학년": 1,
    "학기": 2.0,
    "필수선수": null,
    "권장선수": null,
    "실험실습": null,
    "세부전공": "조형미술",
    "학점": 2.0,
    "시간": 2.0,
    "전공역량": null,
    "대학": "디자인조형학부",
    "학과": "디자인조형학부",
    "개설학과": "디자인조형학부",
    "내용": null,
    "메모": "우수:ARDE283 입체기초조형",
    "개설횟수": 0,
    "syllabus_kr": "",
    "syllabus_en": ""
  },
  {
    "구분": "전공선택",
    "학수번호": "ARDE298",
    "교과목명": "미디어와공간",
    "학년": 2,
    "학기": 1.0,
    "필수선수": null,
    "권장선수": null,
    "실험실습": null,
    "세부전공": "조형미술",
    "학점": 2.0,
    "시간": 2.0,
    "전공역량": null,
    "대학": "디자인조형학부",
    "학과": "디자인조형학부",
    "개설학과": "디자인조형학부",
    "내용": null,
    "메모": "우수:ARDE256 영상과사진",
    "개설횟수": 0,
    "syllabus_kr": "",
    "syllabus_en": ""
  },
  {
    "구분": "전공선택",
    "학수번호": "ARDE235",
    "교과목명": "종이&섬유",
    "학년": 2,
    "학기": 1.0,
    "필수선수": null,
    "권장선수": null,
    "실험실습": null,
    "세부전공": "조형미술",
    "학점": 2.0,
    "시간": 2.0,
    "전공역량": null,
    "대학": "디자인조형학부",
    "학과": "디자인조형학부",
    "개설학과": "디자인조형학부",
    "내용": null,
    "메모": null,
    "개설횟수": 0,
    "syllabus_kr": "",
    "syllabus_en": ""
  },
  {
    "구분": "전공선택",
    "학수번호": "ARDE292",
    "교과목명": "전통회화연구I",
    "학년": 2,
    "학기": 2.0,
    "필수선수": null,
    "권장선수": null,
    "실험실습": null,
    "세부전공": "조형미술",
    "학점": 2.0,
    "시간": 2.0,
    "전공역량": null,
    "대학": "디자인조형학부",
    "학과": "디자인조형학부",
    "개설학과": "디자인조형학부",
    "내용": null,
    "메모": "우수:ARDE261 현대회화연구",
    "개설횟수": 0,
    "syllabus_kr": "",
    "syllabus_en": ""
  },
  {
    "구분": "전공선택",
    "학수번호": "ARDE290",
    "교과목명": "회화STUDIO I",
    "학년": 2,
    "학기": 2.0,
    "필수선수": null,
    "권장선수": null,
    "실험실습": null,
    "세부전공": "조형미술",
    "학점": 2.0,
    "시간": 2.0,
    "전공역량": null,
    "대학": "디자인조형학부",
    "학과": "디자인조형학부",
    "개설학과": "디자인조형학부",
    "내용": null,
    "메모": "우수:ARDE267 회화기법연구",
    "개설횟수": 0,
    "syllabus_kr": "",
    "syllabus_en": ""
  },
  {
    "구분": "전공선택",
    "학수번호": "ARDE259",
    "교과목명": "평면재료기법",
    "학년": 3,
    "학기": 1.0,
    "필수선수": null,
    "권장선수": null,
    "실험실습": null,
    "세부전공": "조형미술",
    "학점": 2.0,
    "시간": 2.0,
    "전공역량": null,
    "대학": "디자인조형학부",
    "학과": "디자인조형학부",
    "개설학과": "디자인조형학부",
    "내용": null,
    "메모": null,
    "개설횟수": 0,
    "syllabus_kr": "",
    "syllabus_en": ""
  },
  {
    "구분": "전공선택",
    "학수번호": "ARDE291",
    "교과목명": "회화STUDIO II",
    "학년": 3,
    "학기": 2.0,
    "필수선수": null,
    "권장선수": null,
    "실험실습": null,
    "세부전공": "조형미술",
    "학점": 2.0,
    "시간": 2.0,
    "전공역량": null,
    "대학": "디자인조형학부",
    "학과": "디자인조형학부",
    "개설학과": "디자인조형학부",
    "내용": null,
    "메모": "우수:ARDE266 회화와아이디어",
    "개설횟수": 0,
    "syllabus_kr": "",
    "syllabus_en": ""
  },
  {
    "구분": "전공선택",
    "학수번호": "ARDE378",
    "교과목명": "현대창작실기 I",
    "학년": 3,
    "학기": 1.0,
    "필수선수": null,
    "권장선수": null,
    "실험실습": null,
    "세부전공": "조형미술",
    "학점": 2.0,
    "시간": 2.0,
    "전공역량": null,
    "대학": "디자인조형학부",
    "학과": "디자인조형학부",
    "개설학과": "디자인조형학부",
    "내용": null,
    "메모": "우수:ARDE262 매체적표현",
    "개설횟수": 0,
    "syllabus_kr": "",
    "syllabus_en": ""
  },
  {
    "구분": "전공선택",
    "학수번호": "ARDE370",
    "교과목명": "신소gud I",
    "학년": 3,
    "학기": 1.0,
    "필수선수": null,
    "권장선수": null,
    "실험실습": null,
    "세부전공": "조형미술",
    "학점": 2.0,
    "시간": 2.0,
    "전공역량": null,
    "대학": "디자인조형학부",
    "학과": "디자인조형학부",
    "개설학과": "디자인조형학부",
    "내용": null,
    "메모": "우수:ARDE364 입체조형STUDIO",
    "개설횟수": 0,
    "syllabus_kr": "",
    "syllabus_en": ""
  },
  {
    "구분": "전공선택",
    "학수번호": "ARDE375",
    "교과목명": "미술사 II",
    "학년": 3,
    "학기": 2.0,
    "필수선수": null,
    "권장선수": null,
    "실험실습": null,
    "세부전공": "조형미술",
    "학점": 2.0,
    "시간": 2.0,
    "전공역량": null,
    "대학": "디자인조형학부",
    "학과": "디자인조형학부",
    "개설학과": "디자인조형학부",
    "내용": null,
    "메모": "우수:ARDE258 전시공간스튜디오",
    "개설횟수": 0,
    "syllabus_kr": "",
    "syllabus_en": ""
  },
  {
    "구분": "전공선택",
    "학수번호": "ARDE379",
    "교과목명": "현대창작실기 II",
    "학년": 3,
    "학기": 2.0,
    "필수선수": null,
    "권장선수": null,
    "실험실습": null,
    "세부전공": "조형미술",
    "학점": 2.0,
    "시간": 2.0,
    "전공역량": null,
    "대학": "디자인조형학부",
    "학과": "디자인조형학부",
    "개설학과": "디자인조형학부",
    "내용": null,
    "메모": "우수:ARDE305 수묵조형(현대적문맥)",
    "개설횟수": 0,
    "syllabus_kr": "",
    "syllabus_en": ""
  },
  {
    "구분": "전공선택",
    "학수번호": "ARDE368",
    "교과목명": "뉴미디어아트",
    "학년": 3,
    "학기": 2.0,
    "필수선수": null,
    "권장선수": null,
    "실험실습": null,
    "세부전공": "조형미술",
    "학점": 2.0,
    "시간": 2.0,
    "전공역량": null,
    "대학": "디자인조형학부",
    "학과": "디자인조형학부",
    "개설학과": "디자인조형학부",
    "내용": null,
    "메모": null,
    "개설횟수": 0,
    "syllabus_kr": "",
    "syllabus_en": ""
  },
  {
    "구분": "전공선택",
    "학수번호": "ARDE377",
    "교과목명": "신소형II",
    "학년": 3,
    "학기": 2.0,
    "필수선수": null,
    "권장선수": null,
    "실험실습": null,
    "세부전공": "조형미술",
    "학점": 2.0,
    "시간": 2.0,
    "전공역량": null,
    "대학": "디자인조형학부",
    "학과": "디자인조형학부",
    "개설학과": "디자인조형학부",
    "내용": null,
    "메모": "우수:ARDE366 장갑조형",
    "개설횟수": 0,
    "syllabus_kr": "",
    "syllabus_en": ""
  },
  {
    "구분": "전공선택",
    "학수번호": "ARDE437",
    "교과목명": "조형론",
    "학년": 4,
    "학기": 1.0,
    "필수선수": null,
    "권장선수": null,
    "실험실습": null,
    "세부전공": "조형미술",
    "학점": 2.0,
    "시간": 2.0,
    "전공역량": null,
    "대학": "디자인조형학부",
    "학과": "디자인조형학부",
    "개설학과": "디자인조형학부",
    "내용": null,
    "메모": null,
    "개설횟수": 0,
    "syllabus_kr": "",
    "syllabus_en": ""
  },
  {
    "구분": "전공선택",
    "학수번호": "ARDE464",
    "교과목명": "개별창작스튜디오",
    "학년": 4,
    "학기": 1.0,
    "필수선수": null,
    "권장선수": null,
    "실험실습": null,
    "세부전공": "조형미술",
    "학점": 2.0,
    "시간": 4.0,
    "전공역량": null,
    "대학": "디자인조형학부",
    "학과": "디자인조형학부",
    "개설학과": "디자인조형학부",
    "내용": null,
    "메모": "우수:ARDE401 FORMS&SPACE",
    "개설횟수": 0,
    "syllabus_kr": "",
    "syllabus_en": ""
  },
  {
    "구분": "전공선택",
    "학수번호": "ARDE463",
    "교과목명": "평면스튜디오",
    "학년": 4,
    "학기": 1.0,
    "필수선수": null,
    "권장선수": null,
    "실험실습": null,
    "세부전공": "조형미술",
    "학점": 2.0,
    "시간": 4.0,
    "전공역량": null,
    "대학": "디자인조형학부",
    "학과": "디자인조형학부",
    "개설학과": "디자인조형학부",
    "내용": null,
    "메모": "우수:ARDE262 테라코타와조형",
    "개설횟수": 0,
    "syllabus_kr": "",
    "syllabus_en": ""
  },
  {
    "구분": "전공선택",
    "학수번호": "ARDE468",
    "교과목명": "한국미술세미나",
    "학년": 4,
    "학기": 2.0,
    "필수선수": null,
    "권장선수": null,
    "실험실습": null,
    "세부전공": "조형미술",
    "학점": 2.0,
    "시간": 2.0,
    "전공역량": null,
    "대학": "디자인조형학부",
    "학과": "디자인조형학부",
    "개설학과": "디자인조형학부",
    "내용": null,
    "메모": "우수:ARDE401 이문화설계연구",
    "개설횟수": 0,
    "syllabus_kr": "",
    "syllabus_en": ""
  },
  {
    "구분": "전공선택",
    "학수번호": "ARDE436",
    "교과목명": "한국화스튜디오 II",
    "학년": 4,
    "학기": 2.0,
    "필수선수": null,
    "권장선수": null,
    "실험실습": null,
    "세부전공": "조형미술",
    "학점": 2.0,
    "시간": 2.0,
    "전공역량": null,
    "대학": "디자인조형학부",
    "학과": "디자인조형학부",
    "개설학과": "디자인조형학부",
    "내용": null,
    "메모": null,
    "개설횟수": 0,
    "syllabus_kr": "",
    "syllabus_en": ""
  },
  {
    "구분": "전공선택",
    "학수번호": "ARDE443",
    "교과목명": "NEW FORMS",
    "학년": 4,
    "학기": 2.0,
    "필수선수": null,
    "권장선수": null,
    "실험실습": null,
    "세부전공": "조형미술",
    "학점": 2.0,
    "시간": 2.0,
    "전공역량": null,
    "대학": "디자인조형학부",
    "학과": "디자인조형학부",
    "개설학과": "디자인조형학부",
    "내용": null,
    "메모": null,
    "개설횟수": 0,
    "syllabus_kr": "",
    "syllabus_en": ""
  },
  {
    "구분": "전공선택",
    "학수번호": "ARDE459",
    "교과목명": "개별작품연구",
    "학년": 4,
    "학기": 2.0,
    "필수선수": null,
    "권장선수": null,
    "실험실습": null,
    "세부전공": "조형미술",
    "학점": 2.0,
    "시간": 4.0,
    "전공역량": null,
    "대학": "디자인조형학부",
    "학과": "디자인조형학부",
    "개설학과": "디자인조형학부",
    "내용": null,
    "메모": "★졸업전필수",
    "개설횟수": 0,
    "syllabus_kr": "",
    "syllabus_en": ""
  }
]
